eric7
