Metadata-Version: 2.4
Name: eric-ide
Version: 26.2
Summary: eric7 is an integrated development environment for the Python language.
Author-email: Detlev Offenbach <detlev@die-offenbachs.de>
Maintainer-email: Detlev Offenbach <detlev@die-offenbachs.de>
License-Expression: GPL-3.0-or-later
Project-URL: Homepage, https://eric-ide.python-projects.org
Project-URL: Donation, https://www.paypal.com/donate/?hosted_button_id=XG3RSPKE3YAJ2
Project-URL: Issues Tracker, https://tracker.die-offenbachs.homelinux.org/
Project-URL: Source Code, https://hg.die-offenbachs.homelinux.org/eric/
Project-URL: Download, https://sourceforge.net/projects/eric-ide/files/latest/download
Project-URL: Mailing List, https://www.riverbankcomputing.com/mailman/listinfo/eric
Project-URL: News, https://eric-ide.python-projects.org/eric-news.html
Keywords: Development,PyQt6,IDE,Python3
Platform: FreeBSD
Platform: Linux
Platform: macOS
Platform: Windows
Classifier: Development Status :: 5 - Production/Stable
Classifier: Environment :: MacOS X
Classifier: Environment :: Win32 (MS Windows)
Classifier: Environment :: X11 Applications
Classifier: Environment :: X11 Applications :: Qt
Classifier: Intended Audience :: Developers
Classifier: Intended Audience :: End Users/Desktop
Classifier: Natural Language :: English
Classifier: Natural Language :: German
Classifier: Natural Language :: Russian
Classifier: Natural Language :: Spanish
Classifier: Operating System :: MacOS :: MacOS X
Classifier: Operating System :: Microsoft :: Windows :: Windows 10
Classifier: Operating System :: Microsoft :: Windows :: Windows 11
Classifier: Operating System :: POSIX :: BSD :: FreeBSD
Classifier: Operating System :: POSIX :: Linux
Classifier: Programming Language :: Python
Classifier: Programming Language :: Python :: 3
Classifier: Programming Language :: Python :: 3.10
Classifier: Programming Language :: Python :: 3.11
Classifier: Programming Language :: Python :: 3.12
Classifier: Programming Language :: Python :: 3.13
Classifier: Programming Language :: Python :: 3.14
Classifier: Programming Language :: Python :: Implementation :: CPython
Classifier: Topic :: Internet :: WWW/HTTP :: Browsers
Classifier: Topic :: Software Development
Classifier: Topic :: Software Development :: Debuggers
Classifier: Topic :: Software Development :: Testing :: Unit
Classifier: Topic :: Software Development :: Version Control :: Git
Classifier: Topic :: Software Development :: Version Control :: Mercurial
Classifier: Topic :: Text Editors :: Integrated Development Environments (IDE)
Requires-Python: <3.15,>=3.10
License-File: docs/LICENSE.txt
Requires-Dist: pip>=21.1
Requires-Dist: wheel
Requires-Dist: PyQt6>=6.8.0
Requires-Dist: PyQt6-Graphs>=6.8.0
Requires-Dist: PyQt6-WebEngine>=6.8.0
Requires-Dist: PyQt6-QScintilla>=2.13.0
Requires-Dist: docutils
Requires-Dist: Markdown
Requires-Dist: esprima
Requires-Dist: pyyaml
Requires-Dist: tomlkit
Requires-Dist: chardet
Requires-Dist: asttokens
Requires-Dist: EditorConfig
Requires-Dist: Pygments
Requires-Dist: parso
Requires-Dist: jedi
Requires-Dist: packaging
Requires-Dist: cyclonedx-bom>=5.4.0
Requires-Dist: trove-classifiers
Requires-Dist: black>=22.6.0
Requires-Dist: isort>=5.10.0
Requires-Dist: coverage>=6.5.0
Requires-Dist: semver
Requires-Dist: pipdeptree
Requires-Dist: watchdog>=5.0.0
Requires-Dist: psutil
Requires-Dist: fido2
Requires-Dist: requests
Requires-Dist: pyusb>=1.2.0
Requires-Dist: spdx-license-list>=3.26.0
Requires-Dist: pywin32>=1.0; platform_system == "Windows"
Requires-Dist: command-runner; platform_system == "Windows"
Dynamic: license-file
